crawlquest/__init__.py
crawlquest/core.py
crawlquest-0.1.3.dist-info/licenses/LICENSE
crawlquest-0.1.3.dist-info/METADATA
crawlquest-0.1.3.dist-info/WHEEL
crawlquest-0.1.3.dist-info/top_level.txt
crawlquest-0.1.3.dist-info/RECORD
