Metadata-Version: 2.4
Name: crawlquest
Version: 0.1.3
Summary: Auto GET/POST web scraping helper for Python requests.
Home-page: https://github.com/leewr9/crawlquest
Author: Rooam
Author-email: leewr9@gmail.com
Classifier: Programming Language :: Python :: 3
Classifier: License :: OSI Approved :: MIT License
Classifier: Operating System :: OS Independent
Requires-Python: >=3.8
License-File: LICENSE
Requires-Dist: requests>=2.25.0
Dynamic: author
Dynamic: author-email
Dynamic: classifier
Dynamic: description
Dynamic: description-content-type
Dynamic: home-page
Dynamic: license-file
Dynamic: requires-dist
Dynamic: requires-python
Dynamic: summary
